{"nodes": [{"id": "src_storage_engine_pager_impl_rs", "label": "impl.rs", "file_type": "code", "source_file": "src/storage/engine/pager/impl.rs", "source_location": "L1"}, {"id": "impl_pager", "label": "Pager", "file_type": "code", "source_file": "src/storage/engine/pager/impl.rs", "source_location": "L6"}, {"id": "impl_pager_open", "label": ".open()", "file_type": "code", "source_file": "src/storage/engine/pager/impl.rs", "source_location": "L8"}, {"id": "impl_pager_open_default", "label": ".open_default()", "file_type": "code", "source_file": "src/storage/engine/pager/impl.rs", "source_location": "L80"}, {"id": "impl_pager_initialize", "label": ".initialize()", "file_type": "code", "source_file": "src/storage/engine/pager/impl.rs", "source_location": "L85"}, {"id": "impl_pager_header_write", "label": ".header_write()", "file_type": "code", "source_file": "src/storage/engine/pager/impl.rs", "source_location": "L103"}, {"id": "impl_pager_header_read", "label": ".header_read()", "file_type": "code", "source_file": "src/storage/engine/pager/impl.rs", "source_location": "L108"}, {"id": "impl_pager_freelist_write", "label": ".freelist_write()", "file_type": "code", "source_file": "src/storage/engine/pager/impl.rs", "source_location": "L113"}, {"id": "impl_pager_file_lock", "label": ".file_lock()", "file_type": "code", "source_file": "src/storage/engine/pager/impl.rs", "source_location": "L118"}, {"id": "impl_pager_header_dirty_lock", "label": ".header_dirty_lock()", "file_type": "code", "source_file": "src/storage/engine/pager/impl.rs", "source_location": "L123"}, {"id": "impl_pager_load_header", "label": ".load_header()", "file_type": "code", "source_file": "src/storage/engine/pager/impl.rs", "source_location": "L130"}, {"id": "impl_pager_write_header", "label": ".write_header()", "file_type": "code", "source_file": "src/storage/engine/pager/impl.rs", "source_location": "L486"}, {"id": "impl_pager_read_page_raw", "label": ".read_page_raw()", "file_type": "code", "source_file": "src/storage/engine/pager/impl.rs", "source_location": "L600"}, {"id": "impl_pager_write_page_raw", "label": ".write_page_raw()", "file_type": "code", "source_file": "src/storage/engine/pager/impl.rs", "source_location": "L620"}, {"id": "impl_pager_read_page", "label": ".read_page()", "file_type": "code", "source_file": "src/storage/engine/pager/impl.rs", "source_location": "L635"}, {"id": "impl_pager_read_page_no_checksum", "label": ".read_page_no_checksum()", "file_type": "code", "source_file": "src/storage/engine/pager/impl.rs", "source_location": "L658"}, {"id": "impl_pager_write_page", "label": ".write_page()", "file_type": "code", "source_file": "src/storage/engine/pager/impl.rs", "source_location": "L687"}, {"id": "impl_pager_write_page_no_checksum", "label": ".write_page_no_checksum()", "file_type": "code", "source_file": "src/storage/engine/pager/impl.rs", "source_location": "L706"}, {"id": "impl_pager_allocate_page", "label": ".allocate_page()", "file_type": "code", "source_file": "src/storage/engine/pager/impl.rs", "source_location": "L719"}, {"id": "impl_pager_free_page", "label": ".free_page()", "file_type": "code", "source_file": "src/storage/engine/pager/impl.rs", "source_location": "L773"}, {"id": "impl_pager_header", "label": ".header()", "file_type": "code", "source_file": "src/storage/engine/pager/impl.rs", "source_location": "L791"}, {"id": "impl_pager_physical_header", "label": ".physical_header()", "file_type": "code", "source_file": "src/storage/engine/pager/impl.rs", "source_location": "L795"}, {"id": "impl_pager_update_physical_header", "label": ".update_physical_header()", "file_type": "code", "source_file": "src/storage/engine/pager/impl.rs", "source_location": "L799"}, {"id": "impl_pager_page_count", "label": ".page_count()", "file_type": "code", "source_file": "src/storage/engine/pager/impl.rs", "source_location": "L811"}, {"id": "impl_pager_set_wal_writer", "label": ".set_wal_writer()", "file_type": "code", "source_file": "src/storage/engine/pager/impl.rs", "source_location": "L826"}, {"id": "impl_pager_clear_wal_writer", "label": ".clear_wal_writer()", "file_type": "code", "source_file": "src/storage/engine/pager/impl.rs", "source_location": "L832"}, {"id": "impl_pager_has_wal_writer", "label": ".has_wal_writer()", "file_type": "code", "source_file": "src/storage/engine/pager/impl.rs", "source_location": "L838"}, {"id": "impl_pager_flush", "label": ".flush()", "file_type": "code", "source_file": "src/storage/engine/pager/impl.rs", "source_location": "L843"}, {"id": "impl_pager_sync", "label": ".sync()", "file_type": "code", "source_file": "src/storage/engine/pager/impl.rs", "source_location": "L910"}, {"id": "impl_pager_cache_stats", "label": ".cache_stats()", "file_type": "code", "source_file": "src/storage/engine/pager/impl.rs", "source_location": "L920"}, {"id": "impl_pager_path", "label": ".path()", "file_type": "code", "source_file": "src/storage/engine/pager/impl.rs", "source_location": "L925"}, {"id": "impl_pager_is_read_only", "label": ".is_read_only()", "file_type": "code", "source_file": "src/storage/engine/pager/impl.rs", "source_location": "L930"}, {"id": "impl_pager_file_size", "label": ".file_size()", "file_type": "code", "source_file": "src/storage/engine/pager/impl.rs", "source_location": "L935"}, {"id": "impl_pager_prefetch_hint", "label": ".prefetch_hint()", "file_type": "code", "source_file": "src/storage/engine/pager/impl.rs", "source_location": "L947"}, {"id": "impl_pager_shadow_path", "label": ".shadow_path()", "file_type": "code", "source_file": "src/storage/engine/pager/impl.rs", "source_location": "L960"}, {"id": "impl_pager_meta_shadow_path", "label": ".meta_shadow_path()", "file_type": "code", "source_file": "src/storage/engine/pager/impl.rs", "source_location": "L967"}, {"id": "impl_pager_dwb_path", "label": ".dwb_path()", "file_type": "code", "source_file": "src/storage/engine/pager/impl.rs", "source_location": "L974"}, {"id": "impl_pager_open_dwb_file", "label": ".open_dwb_file()", "file_type": "code", "source_file": "src/storage/engine/pager/impl.rs", "source_location": "L984"}, {"id": "impl_pager_clear_dwb_file", "label": ".clear_dwb_file()", "file_type": "code", "source_file": "src/storage/engine/pager/impl.rs", "source_location": "L994"}, {"id": "impl_pager_write_header_shadow", "label": ".write_header_shadow()", "file_type": "code", "source_file": "src/storage/engine/pager/impl.rs", "source_location": "L1002"}, {"id": "impl_pager_recover_header_from_shadow", "label": ".recover_header_from_shadow()", "file_type": "code", "source_file": "src/storage/engine/pager/impl.rs", "source_location": "L1014"}, {"id": "impl_pager_write_meta_shadow", "label": ".write_meta_shadow()", "file_type": "code", "source_file": "src/storage/engine/pager/impl.rs", "source_location": "L1045"}, {"id": "impl_pager_recover_meta_from_shadow", "label": ".recover_meta_from_shadow()", "file_type": "code", "source_file": "src/storage/engine/pager/impl.rs", "source_location": "L1057"}, {"id": "impl_pager_write_pages_through_dwb", "label": ".write_pages_through_dwb()", "file_type": "code", "source_file": "src/storage/engine/pager/impl.rs", "source_location": "L1085"}, {"id": "impl_pager_recover_from_dwb", "label": ".recover_from_dwb()", "file_type": "code", "source_file": "src/storage/engine/pager/impl.rs", "source_location": "L1139"}, {"id": "impl_pager_recover_from_dwb_file", "label": ".recover_from_dwb_file()", "file_type": "code", "source_file": "src/storage/engine/pager/impl.rs", "source_location": "L1154"}, {"id": "impl_pager_write_header_and_sync", "label": ".write_header_and_sync()", "file_type": "code", "source_file": "src/storage/engine/pager/impl.rs", "source_location": "L1219"}, {"id": "impl_pager_set_checkpoint_in_progress", "label": ".set_checkpoint_in_progress()", "file_type": "code", "source_file": "src/storage/engine/pager/impl.rs", "source_location": "L1227"}, {"id": "impl_pager_complete_checkpoint", "label": ".complete_checkpoint()", "file_type": "code", "source_file": "src/storage/engine/pager/impl.rs", "source_location": "L1241"}], "edges": [{"source": "src_storage_engine_pager_impl_rs", "target": "super", "relation": "imports_from", "confidence": "EXTRACTED", "source_file": "src/storage/engine/pager/impl.rs", "source_location": "L1", "weight": 1.0}, {"source": "impl_pager", "target": "impl_pager_open", "relation": "method", "confidence": "EXTRACTED", "source_file": "src/storage/engine/pager/impl.rs", "source_location": "L8", "weight": 1.0}, {"source": "impl_pager", "target": "impl_pager_open_default", "relation": "method", "confidence": "EXTRACTED", "source_file": "src/storage/engine/pager/impl.rs", "source_location": "L80", "weight": 1.0}, {"source": "impl_pager", "target": "impl_pager_initialize", "relation": "method", "confidence": "EXTRACTED", "source_file": "src/storage/engine/pager/impl.rs", "source_location": "L85", "weight": 1.0}, {"source": "impl_pager", "target": "impl_pager_header_write", "relation": "method", "confidence": "EXTRACTED", "source_file": "src/storage/engine/pager/impl.rs", "source_location": "L103", "weight": 1.0}, {"source": "impl_pager", "target": "impl_pager_header_read", "relation": "method", "confidence": "EXTRACTED", "source_file": "src/storage/engine/pager/impl.rs", "source_location": "L108", "weight": 1.0}, {"source": "impl_pager", "target": "impl_pager_freelist_write", "relation": "method", "confidence": "EXTRACTED", "source_file": "src/storage/engine/pager/impl.rs", "source_location": "L113", "weight": 1.0}, {"source": "impl_pager", "target": "impl_pager_file_lock", "relation": "method", "confidence": "EXTRACTED", "source_file": "src/storage/engine/pager/impl.rs", "source_location": "L118", "weight": 1.0}, {"source": "impl_pager", "target": "impl_pager_header_dirty_lock", "relation": "method", "confidence": "EXTRACTED", "source_file": "src/storage/engine/pager/impl.rs", "source_location": "L123", "weight": 1.0}, {"source": "impl_pager", "target": "impl_pager_load_header", "relation": "method", "confidence": "EXTRACTED", "source_file": "src/storage/engine/pager/impl.rs", "source_location": "L130", "weight": 1.0}, {"source": "impl_pager", "target": "impl_pager_write_header", "relation": "method", "confidence": "EXTRACTED", "source_file": "src/storage/engine/pager/impl.rs", "source_location": "L486", "weight": 1.0}, {"source": "impl_pager", "target": "impl_pager_read_page_raw", "relation": "method", "confidence": "EXTRACTED", "source_file": "src/storage/engine/pager/impl.rs", "source_location": "L600", "weight": 1.0}, {"source": "impl_pager", "target": "impl_pager_write_page_raw", "relation": "method", "confidence": "EXTRACTED", "source_file": "src/storage/engine/pager/impl.rs", "source_location": "L620", "weight": 1.0}, {"source": "impl_pager", "target": "impl_pager_read_page", "relation": "method", "confidence": "EXTRACTED", "source_file": "src/storage/engine/pager/impl.rs", "source_location": "L635", "weight": 1.0}, {"source": "impl_pager", "target": "impl_pager_read_page_no_checksum", "relation": "method", "confidence": "EXTRACTED", "source_file": "src/storage/engine/pager/impl.rs", "source_location": "L658", "weight": 1.0}, {"source": "impl_pager", "target": "impl_pager_write_page", "relation": "method", "confidence": "EXTRACTED", "source_file": "src/storage/engine/pager/impl.rs", "source_location": "L687", "weight": 1.0}, {"source": "impl_pager", "target": "impl_pager_write_page_no_checksum", "relation": "method", "confidence": "EXTRACTED", "source_file": "src/storage/engine/pager/impl.rs", "source_location": "L706", "weight": 1.0}, {"source": "impl_pager", "target": "impl_pager_allocate_page", "relation": "method", "confidence": "EXTRACTED", "source_file": "src/storage/engine/pager/impl.rs", "source_location": "L719", "weight": 1.0}, {"source": "impl_pager", "target": "impl_pager_free_page", "relation": "method", "confidence": "EXTRACTED", "source_file": "src/storage/engine/pager/impl.rs", "source_location": "L773", "weight": 1.0}, {"source": "impl_pager", "target": "impl_pager_header", "relation": "method", "confidence": "EXTRACTED", "source_file": "src/storage/engine/pager/impl.rs", "source_location": "L791", "weight": 1.0}, {"source": "impl_pager", "target": "impl_pager_physical_header", "relation": "method", "confidence": "EXTRACTED", "source_file": "src/storage/engine/pager/impl.rs", "source_location": "L795", "weight": 1.0}, {"source": "impl_pager", "target": "impl_pager_update_physical_header", "relation": "method", "confidence": "EXTRACTED", "source_file": "src/storage/engine/pager/impl.rs", "source_location": "L799", "weight": 1.0}, {"source": "impl_pager", "target": "impl_pager_page_count", "relation": "method", "confidence": "EXTRACTED", "source_file": "src/storage/engine/pager/impl.rs", "source_location": "L811", "weight": 1.0}, {"source": "impl_pager", "target": "impl_pager_set_wal_writer", "relation": "method", "confidence": "EXTRACTED", "source_file": "src/storage/engine/pager/impl.rs", "source_location": "L826", "weight": 1.0}, {"source": "impl_pager", "target": "impl_pager_clear_wal_writer", "relation": "method", "confidence": "EXTRACTED", "source_file": "src/storage/engine/pager/impl.rs", "source_location": "L832", "weight": 1.0}, {"source": "impl_pager", "target": "impl_pager_has_wal_writer", "relation": "method", "confidence": "EXTRACTED", "source_file": "src/storage/engine/pager/impl.rs", "source_location": "L838", "weight": 1.0}, {"source": "impl_pager", "target": "impl_pager_flush", "relation": "method", "confidence": "EXTRACTED", "source_file": "src/storage/engine/pager/impl.rs", "source_location": "L843", "weight": 1.0}, {"source": "impl_pager", "target": "impl_pager_sync", "relation": "method", "confidence": "EXTRACTED", "source_file": "src/storage/engine/pager/impl.rs", "source_location": "L910", "weight": 1.0}, {"source": "impl_pager", "target": "impl_pager_cache_stats", "relation": "method", "confidence": "EXTRACTED", "source_file": "src/storage/engine/pager/impl.rs", "source_location": "L920", "weight": 1.0}, {"source": "impl_pager", "target": "impl_pager_path", "relation": "method", "confidence": "EXTRACTED", "source_file": "src/storage/engine/pager/impl.rs", "source_location": "L925", "weight": 1.0}, {"source": "impl_pager", "target": "impl_pager_is_read_only", "relation": "method", "confidence": "EXTRACTED", "source_file": "src/storage/engine/pager/impl.rs", "source_location": "L930", "weight": 1.0}, {"source": "impl_pager", "target": "impl_pager_file_size", "relation": "method", "confidence": "EXTRACTED", "source_file": "src/storage/engine/pager/impl.rs", "source_location": "L935", "weight": 1.0}, {"source": "impl_pager", "target": "impl_pager_prefetch_hint", "relation": "method", "confidence": "EXTRACTED", "source_file": "src/storage/engine/pager/impl.rs", "source_location": "L947", "weight": 1.0}, {"source": "impl_pager", "target": "impl_pager_shadow_path", "relation": "method", "confidence": "EXTRACTED", "source_file": "src/storage/engine/pager/impl.rs", "source_location": "L960", "weight": 1.0}, {"source": "impl_pager", "target": "impl_pager_meta_shadow_path", "relation": "method", "confidence": "EXTRACTED", "source_file": "src/storage/engine/pager/impl.rs", "source_location": "L967", "weight": 1.0}, {"source": "impl_pager", "target": "impl_pager_dwb_path", "relation": "method", "confidence": "EXTRACTED", "source_file": "src/storage/engine/pager/impl.rs", "source_location": "L974", "weight": 1.0}, {"source": "impl_pager", "target": "impl_pager_open_dwb_file", "relation": "method", "confidence": "EXTRACTED", "source_file": "src/storage/engine/pager/impl.rs", "source_location": "L984", "weight": 1.0}, {"source": "impl_pager", "target": "impl_pager_clear_dwb_file", "relation": "method", "confidence": "EXTRACTED", "source_file": "src/storage/engine/pager/impl.rs", "source_location": "L994", "weight": 1.0}, {"source": "impl_pager", "target": "impl_pager_write_header_shadow", "relation": "method", "confidence": "EXTRACTED", "source_file": "src/storage/engine/pager/impl.rs", "source_location": "L1002", "weight": 1.0}, {"source": "impl_pager", "target": "impl_pager_recover_header_from_shadow", "relation": "method", "confidence": "EXTRACTED", "source_file": "src/storage/engine/pager/impl.rs", "source_location": "L1014", "weight": 1.0}, {"source": "impl_pager", "target": "impl_pager_write_meta_shadow", "relation": "method", "confidence": "EXTRACTED", "source_file": "src/storage/engine/pager/impl.rs", "source_location": "L1045", "weight": 1.0}, {"source": "impl_pager", "target": "impl_pager_recover_meta_from_shadow", "relation": "method", "confidence": "EXTRACTED", "source_file": "src/storage/engine/pager/impl.rs", "source_location": "L1057", "weight": 1.0}, {"source": "impl_pager", "target": "impl_pager_write_pages_through_dwb", "relation": "method", "confidence": "EXTRACTED", "source_file": "src/storage/engine/pager/impl.rs", "source_location": "L1085", "weight": 1.0}, {"source": "impl_pager", "target": "impl_pager_recover_from_dwb", "relation": "method", "confidence": "EXTRACTED", "source_file": "src/storage/engine/pager/impl.rs", "source_location": "L1139", "weight": 1.0}, {"source": "impl_pager", "target": "impl_pager_recover_from_dwb_file", "relation": "method", "confidence": "EXTRACTED", "source_file": "src/storage/engine/pager/impl.rs", "source_location": "L1154", "weight": 1.0}, {"source": "impl_pager", "target": "impl_pager_write_header_and_sync", "relation": "method", "confidence": "EXTRACTED", "source_file": "src/storage/engine/pager/impl.rs", "source_location": "L1219", "weight": 1.0}, {"source": "impl_pager", "target": "impl_pager_set_checkpoint_in_progress", "relation": "method", "confidence": "EXTRACTED", "source_file": "src/storage/engine/pager/impl.rs", "source_location": "L1227", "weight": 1.0}, {"source": "impl_pager", "target": "impl_pager_complete_checkpoint", "relation": "method", "confidence": "EXTRACTED", "source_file": "src/storage/engine/pager/impl.rs", "source_location": "L1241", "weight": 1.0}, {"source": "impl_pager_open", "target": "impl_pager_open_dwb_file", "relation": "calls", "confidence": "EXTRACTED", "source_file": "src/storage/engine/pager/impl.rs", "source_location": "L47", "weight": 1.0}, {"source": "impl_pager_open", "target": "impl_pager_recover_from_dwb", "relation": "calls", "confidence": "EXTRACTED", "source_file": "src/storage/engine/pager/impl.rs", "source_location": "L68", "weight": 1.0}, {"source": "impl_pager_open", "target": "impl_pager_load_header", "relation": "calls", "confidence": "EXTRACTED", "source_file": "src/storage/engine/pager/impl.rs", "source_location": "L70", "weight": 1.0}, {"source": "impl_pager_open", "target": "impl_pager_initialize", "relation": "calls", "confidence": "EXTRACTED", "source_file": "src/storage/engine/pager/impl.rs", "source_location": "L73", "weight": 1.0}, {"source": "impl_pager_open_default", "target": "impl_pager_open", "relation": "calls", "confidence": "EXTRACTED", "source_file": "src/storage/engine/pager/impl.rs", "source_location": "L81", "weight": 1.0}, {"source": "impl_pager_initialize", "target": "impl_pager_write_page_raw", "relation": "calls", "confidence": "EXTRACTED", "source_file": "src/storage/engine/pager/impl.rs", "source_location": "L94", "weight": 1.0}, {"source": "impl_pager_initialize", "target": "impl_pager_sync", "relation": "calls", "confidence": "EXTRACTED", "source_file": "src/storage/engine/pager/impl.rs", "source_location": "L97", "weight": 1.0}, {"source": "impl_pager_load_header", "target": "impl_pager_read_page_raw", "relation": "calls", "confidence": "EXTRACTED", "source_file": "src/storage/engine/pager/impl.rs", "source_location": "L132", "weight": 1.0}, {"source": "impl_pager_load_header", "target": "impl_pager_recover_header_from_shadow", "relation": "calls", "confidence": "EXTRACTED", "source_file": "src/storage/engine/pager/impl.rs", "source_location": "L140", "weight": 1.0}, {"source": "impl_pager_load_header", "target": "impl_pager_header_write", "relation": "calls", "confidence": "EXTRACTED", "source_file": "src/storage/engine/pager/impl.rs", "source_location": "L432", "weight": 1.0}, {"source": "impl_pager_load_header", "target": "impl_pager_freelist_write", "relation": "calls", "confidence": "EXTRACTED", "source_file": "src/storage/engine/pager/impl.rs", "source_location": "L475", "weight": 1.0}, {"source": "impl_pager_write_header", "target": "impl_pager_header_read", "relation": "calls", "confidence": "EXTRACTED", "source_file": "src/storage/engine/pager/impl.rs", "source_location": "L491", "weight": 1.0}, {"source": "impl_pager_write_header", "target": "impl_pager_file_lock", "relation": "calls", "confidence": "EXTRACTED", "source_file": "src/storage/engine/pager/impl.rs", "source_location": "L499", "weight": 1.0}, {"source": "impl_pager_write_header", "target": "impl_pager_read_page_raw", "relation": "calls", "confidence": "EXTRACTED", "source_file": "src/storage/engine/pager/impl.rs", "source_location": "L504", "weight": 1.0}, {"source": "impl_pager_write_header", "target": "impl_pager_write_header_shadow", "relation": "calls", "confidence": "EXTRACTED", "source_file": "src/storage/engine/pager/impl.rs", "source_location": "L591", "weight": 1.0}, {"source": "impl_pager_write_header", "target": "impl_pager_write_page_raw", "relation": "calls", "confidence": "EXTRACTED", "source_file": "src/storage/engine/pager/impl.rs", "source_location": "L593", "weight": 1.0}, {"source": "impl_pager_write_header", "target": "impl_pager_header_dirty_lock", "relation": "calls", "confidence": "EXTRACTED", "source_file": "src/storage/engine/pager/impl.rs", "source_location": "L594", "weight": 1.0}, {"source": "impl_pager_read_page_raw", "target": "impl_pager_file_lock", "relation": "calls", "confidence": "EXTRACTED", "source_file": "src/storage/engine/pager/impl.rs", "source_location": "L601", "weight": 1.0}, {"source": "impl_pager_write_page_raw", "target": "impl_pager_file_lock", "relation": "calls", "confidence": "EXTRACTED", "source_file": "src/storage/engine/pager/impl.rs", "source_location": "L625", "weight": 1.0}, {"source": "impl_pager_read_page", "target": "impl_pager_read_page_raw", "relation": "calls", "confidence": "EXTRACTED", "source_file": "src/storage/engine/pager/impl.rs", "source_location": "L642", "weight": 1.0}, {"source": "impl_pager_read_page", "target": "impl_pager_write_page_raw", "relation": "calls", "confidence": "EXTRACTED", "source_file": "src/storage/engine/pager/impl.rs", "source_location": "L648", "weight": 1.0}, {"source": "impl_pager_read_page_no_checksum", "target": "impl_pager_file_lock", "relation": "calls", "confidence": "EXTRACTED", "source_file": "src/storage/engine/pager/impl.rs", "source_location": "L665", "weight": 1.0}, {"source": "impl_pager_read_page_no_checksum", "target": "impl_pager_write_page_raw", "relation": "calls", "confidence": "EXTRACTED", "source_file": "src/storage/engine/pager/impl.rs", "source_location": "L680", "weight": 1.0}, {"source": "impl_pager_allocate_page", "target": "impl_pager_freelist_write", "relation": "calls", "confidence": "EXTRACTED", "source_file": "src/storage/engine/pager/impl.rs", "source_location": "L726", "weight": 1.0}, {"source": "impl_pager_allocate_page", "target": "impl_pager_read_page", "relation": "calls", "confidence": "EXTRACTED", "source_file": "src/storage/engine/pager/impl.rs", "source_location": "L733", "weight": 1.0}, {"source": "impl_pager_allocate_page", "target": "impl_pager_header_write", "relation": "calls", "confidence": "EXTRACTED", "source_file": "src/storage/engine/pager/impl.rs", "source_location": "L748", "weight": 1.0}, {"source": "impl_pager_allocate_page", "target": "impl_pager_header_dirty_lock", "relation": "calls", "confidence": "EXTRACTED", "source_file": "src/storage/engine/pager/impl.rs", "source_location": "L750", "weight": 1.0}, {"source": "impl_pager_free_page", "target": "impl_pager_freelist_write", "relation": "calls", "confidence": "EXTRACTED", "source_file": "src/storage/engine/pager/impl.rs", "source_location": "L782", "weight": 1.0}, {"source": "impl_pager_free_page", "target": "impl_pager_header_dirty_lock", "relation": "calls", "confidence": "EXTRACTED", "source_file": "src/storage/engine/pager/impl.rs", "source_location": "L785", "weight": 1.0}, {"source": "impl_pager_header", "target": "impl_pager_header_read", "relation": "calls", "confidence": "EXTRACTED", "source_file": "src/storage/engine/pager/impl.rs", "source_location": "L792", "weight": 1.0}, {"source": "impl_pager_physical_header", "target": "impl_pager_header_read", "relation": "calls", "confidence": "EXTRACTED", "source_file": "src/storage/engine/pager/impl.rs", "source_location": "L796", "weight": 1.0}, {"source": "impl_pager_update_physical_header", "target": "impl_pager_header_write", "relation": "calls", "confidence": "EXTRACTED", "source_file": "src/storage/engine/pager/impl.rs", "source_location": "L804", "weight": 1.0}, {"source": "impl_pager_update_physical_header", "target": "impl_pager_header_dirty_lock", "relation": "calls", "confidence": "EXTRACTED", "source_file": "src/storage/engine/pager/impl.rs", "source_location": "L806", "weight": 1.0}, {"source": "impl_pager_page_count", "target": "impl_pager_header_read", "relation": "calls", "confidence": "EXTRACTED", "source_file": "src/storage/engine/pager/impl.rs", "source_location": "L812", "weight": 1.0}, {"source": "impl_pager_flush", "target": "impl_pager_freelist_write", "relation": "calls", "confidence": "EXTRACTED", "source_file": "src/storage/engine/pager/impl.rs", "source_location": "L850", "weight": 1.0}, {"source": "impl_pager_flush", "target": "impl_pager_header_write", "relation": "calls", "confidence": "EXTRACTED", "source_file": "src/storage/engine/pager/impl.rs", "source_location": "L852", "weight": 1.0}, {"source": "impl_pager_flush", "target": "impl_pager_header_dirty_lock", "relation": "calls", "confidence": "EXTRACTED", "source_file": "src/storage/engine/pager/impl.rs", "source_location": "L859", "weight": 1.0}, {"source": "impl_pager_flush", "target": "impl_pager_header", "relation": "calls", "confidence": "EXTRACTED", "source_file": "src/storage/engine/pager/impl.rs", "source_location": "L882", "weight": 1.0}, {"source": "impl_pager_flush", "target": "impl_pager_write_pages_through_dwb", "relation": "calls", "confidence": "EXTRACTED", "source_file": "src/storage/engine/pager/impl.rs", "source_location": "L898", "weight": 1.0}, {"source": "impl_pager_flush", "target": "impl_pager_write_header", "relation": "calls", "confidence": "EXTRACTED", "source_file": "src/storage/engine/pager/impl.rs", "source_location": "L903", "weight": 1.0}, {"source": "impl_pager_sync", "target": "impl_pager_flush", "relation": "calls", "confidence": "EXTRACTED", "source_file": "src/storage/engine/pager/impl.rs", "source_location": "L911", "weight": 1.0}, {"source": "impl_pager_sync", "target": "impl_pager_file_lock", "relation": "calls", "confidence": "EXTRACTED", "source_file": "src/storage/engine/pager/impl.rs", "source_location": "L913", "weight": 1.0}, {"source": "impl_pager_file_size", "target": "impl_pager_file_lock", "relation": "calls", "confidence": "EXTRACTED", "source_file": "src/storage/engine/pager/impl.rs", "source_location": "L936", "weight": 1.0}, {"source": "impl_pager_prefetch_hint", "target": "impl_pager_file_lock", "relation": "calls", "confidence": "EXTRACTED", "source_file": "src/storage/engine/pager/impl.rs", "source_location": "L948", "weight": 1.0}, {"source": "impl_pager_open_dwb_file", "target": "impl_pager_open", "relation": "calls", "confidence": "EXTRACTED", "source_file": "src/storage/engine/pager/impl.rs", "source_location": "L985", "weight": 1.0}, {"source": "impl_pager_open_dwb_file", "target": "impl_pager_dwb_path", "relation": "calls", "confidence": "EXTRACTED", "source_file": "src/storage/engine/pager/impl.rs", "source_location": "L990", "weight": 1.0}, {"source": "impl_pager_write_header_shadow", "target": "impl_pager_shadow_path", "relation": "calls", "confidence": "EXTRACTED", "source_file": "src/storage/engine/pager/impl.rs", "source_location": "L1006", "weight": 1.0}, {"source": "impl_pager_recover_header_from_shadow", "target": "impl_pager_shadow_path", "relation": "calls", "confidence": "EXTRACTED", "source_file": "src/storage/engine/pager/impl.rs", "source_location": "L1015", "weight": 1.0}, {"source": "impl_pager_recover_header_from_shadow", "target": "impl_pager_open", "relation": "calls", "confidence": "EXTRACTED", "source_file": "src/storage/engine/pager/impl.rs", "source_location": "L1021", "weight": 1.0}, {"source": "impl_pager_recover_header_from_shadow", "target": "impl_pager_write_page_raw", "relation": "calls", "confidence": "EXTRACTED", "source_file": "src/storage/engine/pager/impl.rs", "source_location": "L1036", "weight": 1.0}, {"source": "impl_pager_recover_header_from_shadow", "target": "impl_pager_file_lock", "relation": "calls", "confidence": "EXTRACTED", "source_file": "src/storage/engine/pager/impl.rs", "source_location": "L1037", "weight": 1.0}, {"source": "impl_pager_write_meta_shadow", "target": "impl_pager_meta_shadow_path", "relation": "calls", "confidence": "EXTRACTED", "source_file": "src/storage/engine/pager/impl.rs", "source_location": "L1049", "weight": 1.0}, {"source": "impl_pager_recover_meta_from_shadow", "target": "impl_pager_meta_shadow_path", "relation": "calls", "confidence": "EXTRACTED", "source_file": "src/storage/engine/pager/impl.rs", "source_location": "L1058", "weight": 1.0}, {"source": "impl_pager_recover_meta_from_shadow", "target": "impl_pager_open", "relation": "calls", "confidence": "EXTRACTED", "source_file": "src/storage/engine/pager/impl.rs", "source_location": "L1064", "weight": 1.0}, {"source": "impl_pager_recover_meta_from_shadow", "target": "impl_pager_write_page_raw", "relation": "calls", "confidence": "EXTRACTED", "source_file": "src/storage/engine/pager/impl.rs", "source_location": "L1071", "weight": 1.0}, {"source": "impl_pager_recover_meta_from_shadow", "target": "impl_pager_file_lock", "relation": "calls", "confidence": "EXTRACTED", "source_file": "src/storage/engine/pager/impl.rs", "source_location": "L1072", "weight": 1.0}, {"source": "impl_pager_write_pages_through_dwb", "target": "impl_pager_write_page_raw", "relation": "calls", "confidence": "EXTRACTED", "source_file": "src/storage/engine/pager/impl.rs", "source_location": "L1119", "weight": 1.0}, {"source": "impl_pager_write_pages_through_dwb", "target": "impl_pager_clear_dwb_file", "relation": "calls", "confidence": "EXTRACTED", "source_file": "src/storage/engine/pager/impl.rs", "source_location": "L1123", "weight": 1.0}, {"source": "impl_pager_recover_from_dwb", "target": "impl_pager_dwb_path", "relation": "calls", "confidence": "EXTRACTED", "source_file": "src/storage/engine/pager/impl.rs", "source_location": "L1140", "weight": 1.0}, {"source": "impl_pager_recover_from_dwb", "target": "impl_pager_recover_from_dwb_file", "relation": "calls", "confidence": "EXTRACTED", "source_file": "src/storage/engine/pager/impl.rs", "source_location": "L1147", "weight": 1.0}, {"source": "impl_pager_recover_from_dwb", "target": "impl_pager_open", "relation": "calls", "confidence": "EXTRACTED", "source_file": "src/storage/engine/pager/impl.rs", "source_location": "L1150", "weight": 1.0}, {"source": "impl_pager_recover_from_dwb_file", "target": "impl_pager_clear_dwb_file", "relation": "calls", "confidence": "EXTRACTED", "source_file": "src/storage/engine/pager/impl.rs", "source_location": "L1159", "weight": 1.0}, {"source": "impl_pager_recover_from_dwb_file", "target": "impl_pager_write_page_raw", "relation": "calls", "confidence": "EXTRACTED", "source_file": "src/storage/engine/pager/impl.rs", "source_location": "L1206", "weight": 1.0}, {"source": "impl_pager_recover_from_dwb_file", "target": "impl_pager_file_lock", "relation": "calls", "confidence": "EXTRACTED", "source_file": "src/storage/engine/pager/impl.rs", "source_location": "L1211", "weight": 1.0}, {"source": "impl_pager_write_header_and_sync", "target": "impl_pager_write_header", "relation": "calls", "confidence": "EXTRACTED", "source_file": "src/storage/engine/pager/impl.rs", "source_location": "L1220", "weight": 1.0}, {"source": "impl_pager_write_header_and_sync", "target": "impl_pager_file_lock", "relation": "calls", "confidence": "EXTRACTED", "source_file": "src/storage/engine/pager/impl.rs", "source_location": "L1221", "weight": 1.0}, {"source": "impl_pager_set_checkpoint_in_progress", "target": "impl_pager_header_write", "relation": "calls", "confidence": "EXTRACTED", "source_file": "src/storage/engine/pager/impl.rs", "source_location": "L1232", "weight": 1.0}, {"source": "impl_pager_set_checkpoint_in_progress", "target": "impl_pager_header_dirty_lock", "relation": "calls", "confidence": "EXTRACTED", "source_file": "src/storage/engine/pager/impl.rs", "source_location": "L1235", "weight": 1.0}, {"source": "impl_pager_set_checkpoint_in_progress", "target": "impl_pager_write_header_and_sync", "relation": "calls", "confidence": "EXTRACTED", "source_file": "src/storage/engine/pager/impl.rs", "source_location": "L1237", "weight": 1.0}, {"source": "impl_pager_complete_checkpoint", "target": "impl_pager_header_write", "relation": "calls", "confidence": "EXTRACTED", "source_file": "src/storage/engine/pager/impl.rs", "source_location": "L1242", "weight": 1.0}, {"source": "impl_pager_complete_checkpoint", "target": "impl_pager_header_dirty_lock", "relation": "calls", "confidence": "EXTRACTED", "source_file": "src/storage/engine/pager/impl.rs", "source_location": "L1246", "weight": 1.0}, {"source": "impl_pager_complete_checkpoint", "target": "impl_pager_write_header_and_sync", "relation": "calls", "confidence": "EXTRACTED", "source_file": "src/storage/engine/pager/impl.rs", "source_location": "L1248", "weight": 1.0}], "raw_calls": [{"caller_nid": "impl_pager_open", "callee": "to_path_buf", "source_file": "src/storage/engine/pager/impl.rs", "source_location": "L9"}, {"caller_nid": "impl_pager_open", "callee": "as_ref", "source_file": "src/storage/engine/pager/impl.rs", "source_location": "L9"}, {"caller_nid": "impl_pager_open", "callee": "exists", "source_file": "src/storage/engine/pager/impl.rs", "source_location": "L10"}, {"caller_nid": "impl_pager_open", "callee": "Err", "source_file": "src/storage/engine/pager/impl.rs", "source_location": "L13"}, {"caller_nid": "impl_pager_open", "callee": "InvalidDatabase", "source_file": "src/storage/engine/pager/impl.rs", "source_location": "L13"}, {"caller_nid": "impl_pager_open", "callee": "into", "source_file": "src/storage/engine/pager/impl.rs", "source_location": "L14"}, {"caller_nid": "impl_pager_open", "callee": "Err", "source_file": "src/storage/engine/pager/impl.rs", "source_location": "L19"}, {"caller_nid": "impl_pager_open", "callee": "InvalidDatabase", "source_file": "src/storage/engine/pager/impl.rs", "source_location": "L19"}, {"caller_nid": "impl_pager_open", "callee": "into", "source_file": "src/storage/engine/pager/impl.rs", "source_location": "L20"}, {"caller_nid": "impl_pager_open", "callee": "open", "source_file": "src/storage/engine/pager/impl.rs", "source_location": "L26"}, {"caller_nid": "impl_pager_open", "callee": "create", "source_file": "src/storage/engine/pager/impl.rs", "source_location": "L26"}, {"caller_nid": "impl_pager_open", "callee": "write", "source_file": "src/storage/engine/pager/impl.rs", "source_location": "L26"}, {"caller_nid": "impl_pager_open", "callee": "read", "source_file": "src/storage/engine/pager/impl.rs", "source_location": "L26"}, {"caller_nid": "impl_pager_open", "callee": "new", "source_file": "src/storage/engine/pager/impl.rs", "source_location": "L26"}, {"caller_nid": "impl_pager_open", "callee": "open", "source_file": "src/storage/engine/pager/impl.rs", "source_location": "L34"}, {"caller_nid": "impl_pager_open", "callee": "write", "source_file": "src/storage/engine/pager/impl.rs", "source_location": "L34"}, {"caller_nid": "impl_pager_open", "callee": "read", "source_file": "src/storage/engine/pager/impl.rs", "source_location": "L34"}, {"caller_nid": "impl_pager_open", "callee": "new", "source_file": "src/storage/engine/pager/impl.rs", "source_location": "L34"}, {"caller_nid": "impl_pager_open", "callee": "map_err", "source_file": "src/storage/engine/pager/impl.rs", "source_location": "L35"}, {"caller_nid": "impl_pager_open", "callee": "try_lock_exclusive", "source_file": "src/storage/engine/pager/impl.rs", "source_location": "L35"}, {"caller_nid": "impl_pager_open", "callee": "Some", "source_file": "src/storage/engine/pager/impl.rs", "source_location": "L36"}, {"caller_nid": "impl_pager_open", "callee": "open", "source_file": "src/storage/engine/pager/impl.rs", "source_location": "L38"}, {"caller_nid": "impl_pager_open", "callee": "read", "source_file": "src/storage/engine/pager/impl.rs", "source_location": "L38"}, {"caller_nid": "impl_pager_open", "callee": "new", "source_file": "src/storage/engine/pager/impl.rs", "source_location": "L38"}, {"caller_nid": "impl_pager_open", "callee": "try_lock_shared", "source_file": "src/storage/engine/pager/impl.rs", "source_location": "L39"}, {"caller_nid": "impl_pager_open", "callee": "Some", "source_file": "src/storage/engine/pager/impl.rs", "source_location": "L40"}, {"caller_nid": "impl_pager_open", "callee": "Some", "source_file": "src/storage/engine/pager/impl.rs", "source_location": "L48"}, {"caller_nid": "impl_pager_open", "callee": "new", "source_file": "src/storage/engine/pager/impl.rs", "source_location": "L48"}, {"caller_nid": "impl_pager_open", "callee": "new", "source_file": "src/storage/engine/pager/impl.rs", "source_location": "L55"}, {"caller_nid": "impl_pager_open", "callee": "new", "source_file": "src/storage/engine/pager/impl.rs", "source_location": "L58"}, {"caller_nid": "impl_pager_open", "callee": "new", "source_file": "src/storage/engine/pager/impl.rs", "source_location": "L59"}, {"caller_nid": "impl_pager_open", "callee": "new", "source_file": "src/storage/engine/pager/impl.rs", "source_location": "L59"}, {"caller_nid": "impl_pager_open", "callee": "new", "source_file": "src/storage/engine/pager/impl.rs", "source_location": "L60"}, {"caller_nid": "impl_pager_open", "callee": "default", "source_file": "src/storage/engine/pager/impl.rs", "source_location": "L60"}, {"caller_nid": "impl_pager_open", "callee": "new", "source_file": "src/storage/engine/pager/impl.rs", "source_location": "L62"}, {"caller_nid": "impl_pager_open", "callee": "new", "source_file": "src/storage/engine/pager/impl.rs", "source_location": "L63"}, {"caller_nid": "impl_pager_open", "callee": "Ok", "source_file": "src/storage/engine/pager/impl.rs", "source_location": "L76"}, {"caller_nid": "impl_pager_open_default", "callee": "default", "source_file": "src/storage/engine/pager/impl.rs", "source_location": "L81"}, {"caller_nid": "impl_pager_initialize", "callee": "Err", "source_file": "src/storage/engine/pager/impl.rs", "source_location": "L87"}, {"caller_nid": "impl_pager_initialize", "callee": "new_header_page", "source_file": "src/storage/engine/pager/impl.rs", "source_location": "L91"}, {"caller_nid": "impl_pager_initialize", "callee": "Ok", "source_file": "src/storage/engine/pager/impl.rs", "source_location": "L99"}, {"caller_nid": "impl_pager_header_write", "callee": "map_err", "source_file": "src/storage/engine/pager/impl.rs", "source_location": "L104"}, {"caller_nid": "impl_pager_header_write", "callee": "write", "source_file": "src/storage/engine/pager/impl.rs", "source_location": "L104"}, {"caller_nid": "impl_pager_header_read", "callee": "map_err", "source_file": "src/storage/engine/pager/impl.rs", "source_location": "L109"}, {"caller_nid": "impl_pager_header_read", "callee": "read", "source_file": "src/storage/engine/pager/impl.rs", "source_location": "L109"}, {"caller_nid": "impl_pager_freelist_write", "callee": "map_err", "source_file": "src/storage/engine/pager/impl.rs", "source_location": "L114"}, {"caller_nid": "impl_pager_freelist_write", "callee": "write", "source_file": "src/storage/engine/pager/impl.rs", "source_location": "L114"}, {"caller_nid": "impl_pager_file_lock", "callee": "map_err", "source_file": "src/storage/engine/pager/impl.rs", "source_location": "L119"}, {"caller_nid": "impl_pager_file_lock", "callee": "lock", "source_file": "src/storage/engine/pager/impl.rs", "source_location": "L119"}, {"caller_nid": "impl_pager_header_dirty_lock", "callee": "map_err", "source_file": "src/storage/engine/pager/impl.rs", "source_location": "L124"}, {"caller_nid": "impl_pager_header_dirty_lock", "callee": "lock", "source_file": "src/storage/engine/pager/impl.rs", "source_location": "L124"}, {"caller_nid": "impl_pager_load_header", "callee": "as_bytes", "source_file": "src/storage/engine/pager/impl.rs", "source_location": "L135"}, {"caller_nid": "impl_pager_load_header", "callee": "as_bytes", "source_file": "src/storage/engine/pager/impl.rs", "source_location": "L147"}, {"caller_nid": "impl_pager_load_header", "callee": "from_le_bytes", "source_file": "src/storage/engine/pager/impl.rs", "source_location": "L148"}, {"caller_nid": "impl_pager_load_header", "callee": "from_le_bytes", "source_file": "src/storage/engine/pager/impl.rs", "source_location": "L155"}, {"caller_nid": "impl_pager_load_header", "callee": "Err", "source_file": "src/storage/engine/pager/impl.rs", "source_location": "L163"}, {"caller_nid": "impl_pager_load_header", "callee": "InvalidDatabase", "source_file": "src/storage/engine/pager/impl.rs", "source_location": "L163"}, {"caller_nid": "impl_pager_load_header", "callee": "from_le_bytes", "source_file": "src/storage/engine/pager/impl.rs", "source_location": "L169"}, {"caller_nid": "impl_pager_load_header", "callee": "from_le_bytes", "source_file": "src/storage/engine/pager/impl.rs", "source_location": "L176"}, {"caller_nid": "impl_pager_load_header", "callee": "from_le_bytes", "source_file": "src/storage/engine/pager/impl.rs", "source_location": "L183"}, {"caller_nid": "impl_pager_load_header", "callee": "from_le_bytes", "source_file": "src/storage/engine/pager/impl.rs", "source_location": "L190"}, {"caller_nid": "impl_pager_load_header", "callee": "from_le_bytes", "source_file": "src/storage/engine/pager/impl.rs", "source_location": "L200"}, {"caller_nid": "impl_pager_load_header", "callee": "from_le_bytes", "source_file": "src/storage/engine/pager/impl.rs", "source_location": "L206"}, {"caller_nid": "impl_pager_load_header", "callee": "from_le_bytes", "source_file": "src/storage/engine/pager/impl.rs", "source_location": "L216"}, {"caller_nid": "impl_pager_load_header", "callee": "from_le_bytes", "source_file": "src/storage/engine/pager/impl.rs", "source_location": "L226"}, {"caller_nid": "impl_pager_load_header", "callee": "from_le_bytes", "source_file": "src/storage/engine/pager/impl.rs", "source_location": "L236"}, {"caller_nid": "impl_pager_load_header", "callee": "from_le_bytes", "source_file": "src/storage/engine/pager/impl.rs", "source_location": "L246"}, {"caller_nid": "impl_pager_load_header", "callee": "from_le_bytes", "source_file": "src/storage/engine/pager/impl.rs", "source_location": "L252"}, {"caller_nid": "impl_pager_load_header", "callee": "from_le_bytes", "source_file": "src/storage/engine/pager/impl.rs", "source_location": "L262"}, {"caller_nid": "impl_pager_load_header", "callee": "from_le_bytes", "source_file": "src/storage/engine/pager/impl.rs", "source_location": "L268"}, {"caller_nid": "impl_pager_load_header", "callee": "from_le_bytes", "source_file": "src/storage/engine/pager/impl.rs", "source_location": "L278"}, {"caller_nid": "impl_pager_load_header", "callee": "from_le_bytes", "source_file": "src/storage/engine/pager/impl.rs", "source_location": "L284"}, {"caller_nid": "impl_pager_load_header", "callee": "from_le_bytes", "source_file": "src/storage/engine/pager/impl.rs", "source_location": "L290"}, {"caller_nid": "impl_pager_load_header", "callee": "from_le_bytes", "source_file": "src/storage/engine/pager/impl.rs", "source_location": "L296"}, {"caller_nid": "impl_pager_load_header", "callee": "from_le_bytes", "source_file": "src/storage/engine/pager/impl.rs", "source_location": "L302"}, {"caller_nid": "impl_pager_load_header", "callee": "from_le_bytes", "source_file": "src/storage/engine/pager/impl.rs", "source_location": "L312"}, {"caller_nid": "impl_pager_load_header", "callee": "from_le_bytes", "source_file": "src/storage/engine/pager/impl.rs", "source_location": "L318"}, {"caller_nid": "impl_pager_load_header", "callee": "from_le_bytes", "source_file": "src/storage/engine/pager/impl.rs", "source_location": "L324"}, {"caller_nid": "impl_pager_load_header", "callee": "from_le_bytes", "source_file": "src/storage/engine/pager/impl.rs", "source_location": "L330"}, {"caller_nid": "impl_pager_load_header", "callee": "from_le_bytes", "source_file": "src/storage/engine/pager/impl.rs", "source_location": "L336"}, {"caller_nid": "impl_pager_load_header", "callee": "from_le_bytes", "source_file": "src/storage/engine/pager/impl.rs", "source_location": "L342"}, {"caller_nid": "impl_pager_load_header", "callee": "from_le_bytes", "source_file": "src/storage/engine/pager/impl.rs", "source_location": "L352"}, {"caller_nid": "impl_pager_load_header", "callee": "from_le_bytes", "source_file": "src/storage/engine/pager/impl.rs", "source_location": "L358"}, {"caller_nid": "impl_pager_load_header", "callee": "from_le_bytes", "source_file": "src/storage/engine/pager/impl.rs", "source_location": "L368"}, {"caller_nid": "impl_pager_load_header", "callee": "from_le_bytes", "source_file": "src/storage/engine/pager/impl.rs", "source_location": "L374"}, {"caller_nid": "impl_pager_load_header", "callee": "from_le_bytes", "source_file": "src/storage/engine/pager/impl.rs", "source_location": "L384"}, {"caller_nid": "impl_pager_load_header", "callee": "from_le_bytes", "source_file": "src/storage/engine/pager/impl.rs", "source_location": "L390"}, {"caller_nid": "impl_pager_load_header", "callee": "from_le_bytes", "source_file": "src/storage/engine/pager/impl.rs", "source_location": "L400"}, {"caller_nid": "impl_pager_load_header", "callee": "from_le_bytes", "source_file": "src/storage/engine/pager/impl.rs", "source_location": "L406"}, {"caller_nid": "impl_pager_load_header", "callee": "from_le_bytes", "source_file": "src/storage/engine/pager/impl.rs", "source_location": "L419"}, {"caller_nid": "impl_pager_load_header", "callee": "from_header", "source_file": "src/storage/engine/pager/impl.rs", "source_location": "L476"}, {"caller_nid": "impl_pager_load_header", "callee": "Ok", "source_file": "src/storage/engine/pager/impl.rs", "source_location": "L479"}, {"caller_nid": "impl_pager_write_header", "callee": "Err", "source_file": "src/storage/engine/pager/impl.rs", "source_location": "L488"}, {"caller_nid": "impl_pager_write_header", "callee": "get", "source_file": "src/storage/engine/pager/impl.rs", "source_location": "L495"}, {"caller_nid": "impl_pager_write_header", "callee": "unwrap_or", "source_file": "src/storage/engine/pager/impl.rs", "source_location": "L500"}, {"caller_nid": "impl_pager_write_header", "callee": "map", "source_file": "src/storage/engine/pager/impl.rs", "source_location": "L500"}, {"caller_nid": "impl_pager_write_header", "callee": "metadata", "source_file": "src/storage/engine/pager/impl.rs", "source_location": "L500"}, {"caller_nid": "impl_pager_write_header", "callee": "len", "source_file": "src/storage/engine/pager/impl.rs", "source_location": "L500"}, {"caller_nid": "impl_pager_write_header", "callee": "drop", "source_file": "src/storage/engine/pager/impl.rs", "source_location": "L501"}, {"caller_nid": "impl_pager_write_header", "callee": "new", "source_file": "src/storage/engine/pager/impl.rs", "source_location": "L507"}, {"caller_nid": "impl_pager_write_header", "callee": "as_bytes_mut", "source_file": "src/storage/engine/pager/impl.rs", "source_location": "L511"}, {"caller_nid": "impl_pager_write_header", "callee": "copy_from_slice", "source_file": "src/storage/engine/pager/impl.rs", "source_location": "L514"}, {"caller_nid": "impl_pager_write_header", "callee": "copy_from_slice", "source_file": "src/storage/engine/pager/impl.rs", "source_location": "L517"}, {"caller_nid": "impl_pager_write_header", "callee": "to_le_bytes", "source_file": "src/storage/engine/pager/impl.rs", "source_location": "L517"}, {"caller_nid": "impl_pager_write_header", "callee": "copy_from_slice", "source_file": "src/storage/engine/pager/impl.rs", "source_location": "L518"}, {"caller_nid": "impl_pager_write_header", "callee": "to_le_bytes", "source_file": "src/storage/engine/pager/impl.rs", "source_location": "L518"}, {"caller_nid": "impl_pager_write_header", "callee": "copy_from_slice", "source_file": "src/storage/engine/pager/impl.rs", "source_location": "L519"}, {"caller_nid": "impl_pager_write_header", "callee": "to_le_bytes", "source_file": "src/storage/engine/pager/impl.rs", "source_location": "L519"}, {"caller_nid": "impl_pager_write_header", "callee": "copy_from_slice", "source_file": "src/storage/engine/pager/impl.rs", "source_location": "L520"}, {"caller_nid": "impl_pager_write_header", "callee": "to_le_bytes", "source_file": "src/storage/engine/pager/impl.rs", "source_location": "L521"}, {"caller_nid": "impl_pager_write_header", "callee": "copy_from_slice", "source_file": "src/storage/engine/pager/impl.rs", "source_location": "L522"}, {"caller_nid": "impl_pager_write_header", "callee": "to_le_bytes", "source_file": "src/storage/engine/pager/impl.rs", "source_location": "L523"}, {"caller_nid": "impl_pager_write_header", "callee": "copy_from_slice", "source_file": "src/storage/engine/pager/impl.rs", "source_location": "L524"}, {"caller_nid": "impl_pager_write_header", "callee": "to_le_bytes", "source_file": "src/storage/engine/pager/impl.rs", "source_location": "L525"}, {"caller_nid": "impl_pager_write_header", "callee": "copy_from_slice", "source_file": "src/storage/engine/pager/impl.rs", "source_location": "L526"}, {"caller_nid": "impl_pager_write_header", "callee": "to_le_bytes", "source_file": "src/storage/engine/pager/impl.rs", "source_location": "L527"}, {"caller_nid": "impl_pager_write_header", "callee": "copy_from_slice", "source_file": "src/storage/engine/pager/impl.rs", "source_location": "L528"}, {"caller_nid": "impl_pager_write_header", "callee": "to_le_bytes", "source_file": "src/storage/engine/pager/impl.rs", "source_location": "L529"}, {"caller_nid": "impl_pager_write_header", "callee": "copy_from_slice", "source_file": "src/storage/engine/pager/impl.rs", "source_location": "L530"}, {"caller_nid": "impl_pager_write_header", "callee": "to_le_bytes", "source_file": "src/storage/engine/pager/impl.rs", "source_location": "L531"}, {"caller_nid": "impl_pager_write_header", "callee": "copy_from_slice", "source_file": "src/storage/engine/pager/impl.rs", "source_location": "L532"}, {"caller_nid": "impl_pager_write_header", "callee": "to_le_bytes", "source_file": "src/storage/engine/pager/impl.rs", "source_location": "L533"}, {"caller_nid": "impl_pager_write_header", "callee": "copy_from_slice", "source_file": "src/storage/engine/pager/impl.rs", "source_location": "L534"}, {"caller_nid": "impl_pager_write_header", "callee": "to_le_bytes", "source_file": "src/storage/engine/pager/impl.rs", "source_location": "L535"}, {"caller_nid": "impl_pager_write_header", "callee": "copy_from_slice", "source_file": "src/storage/engine/pager/impl.rs", "source_location": "L536"}, {"caller_nid": "impl_pager_write_header", "callee": "to_le_bytes", "source_file": "src/storage/engine/pager/impl.rs", "source_location": "L537"}, {"caller_nid": "impl_pager_write_header", "callee": "copy_from_slice", "source_file": "src/storage/engine/pager/impl.rs", "source_location": "L538"}, {"caller_nid": "impl_pager_write_header", "callee": "to_le_bytes", "source_file": "src/storage/engine/pager/impl.rs", "source_location": "L539"}, {"caller_nid": "impl_pager_write_header", "callee": "copy_from_slice", "source_file": "src/storage/engine/pager/impl.rs", "source_location": "L540"}, {"caller_nid": "impl_pager_write_header", "callee": "to_le_bytes", "source_file": "src/storage/engine/pager/impl.rs", "source_location": "L541"}, {"caller_nid": "impl_pager_write_header", "callee": "copy_from_slice", "source_file": "src/storage/engine/pager/impl.rs", "source_location": "L542"}, {"caller_nid": "impl_pager_write_header", "callee": "to_le_bytes", "source_file": "src/storage/engine/pager/impl.rs", "source_location": "L543"}, {"caller_nid": "impl_pager_write_header", "callee": "copy_from_slice", "source_file": "src/storage/engine/pager/impl.rs", "source_location": "L544"}, {"caller_nid": "impl_pager_write_header", "callee": "to_le_bytes", "source_file": "src/storage/engine/pager/impl.rs", "source_location": "L545"}, {"caller_nid": "impl_pager_write_header", "callee": "copy_from_slice", "source_file": "src/storage/engine/pager/impl.rs", "source_location": "L546"}, {"caller_nid": "impl_pager_write_header", "callee": "to_le_bytes", "source_file": "src/storage/engine/pager/impl.rs", "source_location": "L547"}, {"caller_nid": "impl_pager_write_header", "callee": "copy_from_slice", "source_file": "src/storage/engine/pager/impl.rs", "source_location": "L548"}, {"caller_nid": "impl_pager_write_header", "callee": "to_le_bytes", "source_file": "src/storage/engine/pager/impl.rs", "source_location": "L549"}, {"caller_nid": "impl_pager_write_header", "callee": "copy_from_slice", "source_file": "src/storage/engine/pager/impl.rs", "source_location": "L550"}, {"caller_nid": "impl_pager_write_header", "callee": "to_le_bytes", "source_file": "src/storage/engine/pager/impl.rs", "source_location": "L551"}, {"caller_nid": "impl_pager_write_header", "callee": "copy_from_slice", "source_file": "src/storage/engine/pager/impl.rs", "source_location": "L552"}, {"caller_nid": "impl_pager_write_header", "callee": "to_le_bytes", "source_file": "src/storage/engine/pager/impl.rs", "source_location": "L553"}, {"caller_nid": "impl_pager_write_header", "callee": "copy_from_slice", "source_file": "src/storage/engine/pager/impl.rs", "source_location": "L554"}, {"caller_nid": "impl_pager_write_header", "callee": "to_le_bytes", "source_file": "src/storage/engine/pager/impl.rs", "source_location": "L555"}, {"caller_nid": "impl_pager_write_header", "callee": "copy_from_slice", "source_file": "src/storage/engine/pager/impl.rs", "source_location": "L556"}, {"caller_nid": "impl_pager_write_header", "callee": "to_le_bytes", "source_file": "src/storage/engine/pager/impl.rs", "source_location": "L557"}, {"caller_nid": "impl_pager_write_header", "callee": "copy_from_slice", "source_file": "src/storage/engine/pager/impl.rs", "source_location": "L558"}, {"caller_nid": "impl_pager_write_header", "callee": "to_le_bytes", "source_file": "src/storage/engine/pager/impl.rs", "source_location": "L559"}, {"caller_nid": "impl_pager_write_header", "callee": "copy_from_slice", "source_file": "src/storage/engine/pager/impl.rs", "source_location": "L560"}, {"caller_nid": "impl_pager_write_header", "callee": "to_le_bytes", "source_file": "src/storage/engine/pager/impl.rs", "source_location": "L561"}, {"caller_nid": "impl_pager_write_header", "callee": "copy_from_slice", "source_file": "src/storage/engine/pager/impl.rs", "source_location": "L562"}, {"caller_nid": "impl_pager_write_header", "callee": "to_le_bytes", "source_file": "src/storage/engine/pager/impl.rs", "source_location": "L563"}, {"caller_nid": "impl_pager_write_header", "callee": "copy_from_slice", "source_file": "src/storage/engine/pager/impl.rs", "source_location": "L564"}, {"caller_nid": "impl_pager_write_header", "callee": "to_le_bytes", "source_file": "src/storage/engine/pager/impl.rs", "source_location": "L565"}, {"caller_nid": "impl_pager_write_header", "callee": "copy_from_slice", "source_file": "src/storage/engine/pager/impl.rs", "source_location": "L566"}, {"caller_nid": "impl_pager_write_header", "callee": "to_le_bytes", "source_file": "src/storage/engine/pager/impl.rs", "source_location": "L567"}, {"caller_nid": "impl_pager_write_header", "callee": "copy_from_slice", "source_file": "src/storage/engine/pager/impl.rs", "source_location": "L568"}, {"caller_nid": "impl_pager_write_header", "callee": "to_le_bytes", "source_file": "src/storage/engine/pager/impl.rs", "source_location": "L569"}, {"caller_nid": "impl_pager_write_header", "callee": "copy_from_slice", "source_file": "src/storage/engine/pager/impl.rs", "source_location": "L570"}, {"caller_nid": "impl_pager_write_header", "callee": "to_le_bytes", "source_file": "src/storage/engine/pager/impl.rs", "source_location": "L571"}, {"caller_nid": "impl_pager_write_header", "callee": "copy_from_slice", "source_file": "src/storage/engine/pager/impl.rs", "source_location": "L572"}, {"caller_nid": "impl_pager_write_header", "callee": "to_le_bytes", "source_file": "src/storage/engine/pager/impl.rs", "source_location": "L573"}, {"caller_nid": "impl_pager_write_header", "callee": "copy_from_slice", "source_file": "src/storage/engine/pager/impl.rs", "source_location": "L574"}, {"caller_nid": "impl_pager_write_header", "callee": "to_le_bytes", "source_file": "src/storage/engine/pager/impl.rs", "source_location": "L575"}, {"caller_nid": "impl_pager_write_header", "callee": "copy_from_slice", "source_file": "src/storage/engine/pager/impl.rs", "source_location": "L576"}, {"caller_nid": "impl_pager_write_header", "callee": "to_le_bytes", "source_file": "src/storage/engine/pager/impl.rs", "source_location": "L577"}, {"caller_nid": "impl_pager_write_header", "callee": "copy_from_slice", "source_file": "src/storage/engine/pager/impl.rs", "source_location": "L578"}, {"caller_nid": "impl_pager_write_header", "callee": "to_le_bytes", "source_file": "src/storage/engine/pager/impl.rs", "source_location": "L579"}, {"caller_nid": "impl_pager_write_header", "callee": "copy_from_slice", "source_file": "src/storage/engine/pager/impl.rs", "source_location": "L580"}, {"caller_nid": "impl_pager_write_header", "callee": "to_le_bytes", "source_file": "src/storage/engine/pager/impl.rs", "source_location": "L581"}, {"caller_nid": "impl_pager_write_header", "callee": "copy_from_slice", "source_file": "src/storage/engine/pager/impl.rs", "source_location": "L585"}, {"caller_nid": "impl_pager_write_header", "callee": "to_le_bytes", "source_file": "src/storage/engine/pager/impl.rs", "source_location": "L586"}, {"caller_nid": "impl_pager_write_header", "callee": "update_checksum", "source_file": "src/storage/engine/pager/impl.rs", "source_location": "L588"}, {"caller_nid": "impl_pager_write_header", "callee": "Ok", "source_file": "src/storage/engine/pager/impl.rs", "source_location": "L596"}, {"caller_nid": "impl_pager_read_page_raw", "callee": "seek", "source_file": "src/storage/engine/pager/impl.rs", "source_location": "L604"}, {"caller_nid": "impl_pager_read_page_raw", "callee": "Start", "source_file": "src/storage/engine/pager/impl.rs", "source_location": "L604"}, {"caller_nid": "impl_pager_read_page_raw", "callee": "read_exact", "source_file": "src/storage/engine/pager/impl.rs", "source_location": "L607"}, {"caller_nid": "impl_pager_read_page_raw", "callee": "from_bytes", "source_file": "src/storage/engine/pager/impl.rs", "source_location": "L609"}, {"caller_nid": "impl_pager_read_page_raw", "callee": "verify_checksum", "source_file": "src/storage/engine/pager/impl.rs", "source_location": "L613"}, {"caller_nid": "impl_pager_read_page_raw", "callee": "Ok", "source_file": "src/storage/engine/pager/impl.rs", "source_location": "L616"}, {"caller_nid": "impl_pager_write_page_raw", "callee": "Err", "source_file": "src/storage/engine/pager/impl.rs", "source_location": "L622"}, {"caller_nid": "impl_pager_write_page_raw", "callee": "seek", "source_file": "src/storage/engine/pager/impl.rs", "source_location": "L628"}, {"caller_nid": "impl_pager_write_page_raw", "callee": "Start", "source_file": "src/storage/engine/pager/impl.rs", "source_location": "L628"}, {"caller_nid": "impl_pager_write_page_raw", "callee": "write_all", "source_file": "src/storage/engine/pager/impl.rs", "source_location": "L629"}, {"caller_nid": "impl_pager_write_page_raw", "callee": "as_bytes", "source_file": "src/storage/engine/pager/impl.rs", "source_location": "L629"}, {"caller_nid": "impl_pager_write_page_raw", "callee": "Ok", "source_file": "src/storage/engine/pager/impl.rs", "source_location": "L631"}, {"caller_nid": "impl_pager_read_page", "callee": "get", "source_file": "src/storage/engine/pager/impl.rs", "source_location": "L637"}, {"caller_nid": "impl_pager_read_page", "callee": "Ok", "source_file": "src/storage/engine/pager/impl.rs", "source_location": "L638"}, {"caller_nid": "impl_pager_read_page", "callee": "insert", "source_file": "src/storage/engine/pager/impl.rs", "source_location": "L645"}, {"caller_nid": "impl_pager_read_page", "callee": "clone", "source_file": "src/storage/engine/pager/impl.rs", "source_location": "L645"}, {"caller_nid": "impl_pager_read_page", "callee": "page_id", "source_file": "src/storage/engine/pager/impl.rs", "source_location": "L647"}, {"caller_nid": "impl_pager_read_page", "callee": "Ok", "source_file": "src/storage/engine/pager/impl.rs", "source_location": "L651"}, {"caller_nid": "impl_pager_read_page_no_checksum", "callee": "get", "source_file": "src/storage/engine/pager/impl.rs", "source_location": "L660"}, {"caller_nid": "impl_pager_read_page_no_checksum", "callee": "Ok", "source_file": "src/storage/engine/pager/impl.rs", "source_location": "L661"}, {"caller_nid": "impl_pager_read_page_no_checksum", "callee": "seek", "source_file": "src/storage/engine/pager/impl.rs", "source_location": "L668"}, {"caller_nid": "impl_pager_read_page_no_checksum", "callee": "Start", "source_file": "src/storage/engine/pager/impl.rs", "source_location": "L668"}, {"caller_nid": "impl_pager_read_page_no_checksum", "callee": "read_exact", "source_file": "src/storage/engine/pager/impl.rs", "source_location": "L671"}, {"caller_nid": "impl_pager_read_page_no_checksum", "callee": "drop", "source_file": "src/storage/engine/pager/impl.rs", "source_location": "L672"}, {"caller_nid": "impl_pager_read_page_no_checksum", "callee": "from_bytes", "source_file": "src/storage/engine/pager/impl.rs", "source_location": "L674"}, {"caller_nid": "impl_pager_read_page_no_checksum", "callee": "insert", "source_file": "src/storage/engine/pager/impl.rs", "source_location": "L677"}, {"caller_nid": "impl_pager_read_page_no_checksum", "callee": "clone", "source_file": "src/storage/engine/pager/impl.rs", "source_location": "L677"}, {"caller_nid": "impl_pager_read_page_no_checksum", "callee": "page_id", "source_file": "src/storage/engine/pager/impl.rs", "source_location": "L679"}, {"caller_nid": "impl_pager_read_page_no_checksum", "callee": "Ok", "source_file": "src/storage/engine/pager/impl.rs", "source_location": "L683"}, {"caller_nid": "impl_pager_write_page", "callee": "Err", "source_file": "src/storage/engine/pager/impl.rs", "source_location": "L689"}, {"caller_nid": "impl_pager_write_page", "callee": "update_checksum", "source_file": "src/storage/engine/pager/impl.rs", "source_location": "L693"}, {"caller_nid": "impl_pager_write_page", "callee": "insert", "source_file": "src/storage/engine/pager/impl.rs", "source_location": "L696"}, {"caller_nid": "impl_pager_write_page", "callee": "mark_dirty", "source_file": "src/storage/engine/pager/impl.rs", "source_location": "L697"}, {"caller_nid": "impl_pager_write_page", "callee": "Ok", "source_file": "src/storage/engine/pager/impl.rs", "source_location": "L699"}, {"caller_nid": "impl_pager_write_page_no_checksum", "callee": "Err", "source_file": "src/storage/engine/pager/impl.rs", "source_location": "L708"}, {"caller_nid": "impl_pager_write_page_no_checksum", "callee": "insert", "source_file": "src/storage/engine/pager/impl.rs", "source_location": "L712"}, {"caller_nid": "impl_pager_write_page_no_checksum", "callee": "mark_dirty", "source_file": "src/storage/engine/pager/impl.rs", "source_location": "L713"}, {"caller_nid": "impl_pager_write_page_no_checksum", "callee": "Ok", "source_file": "src/storage/engine/pager/impl.rs", "source_location": "L715"}, {"caller_nid": "impl_pager_allocate_page", "callee": "Err", "source_file": "src/storage/engine/pager/impl.rs", "source_location": "L721"}, {"caller_nid": "impl_pager_allocate_page", "callee": "allocate", "source_file": "src/storage/engine/pager/impl.rs", "source_location": "L727"}, {"caller_nid": "impl_pager_allocate_page", "callee": "trunk_head", "source_file": "src/storage/engine/pager/impl.rs", "source_location": "L729"}, {"caller_nid": "impl_pager_allocate_page", "callee": "trunk_head", "source_file": "src/storage/engine/pager/impl.rs", "source_location": "L730"}, {"caller_nid": "impl_pager_allocate_page", "callee": "drop", "source_file": "src/storage/engine/pager/impl.rs", "source_location": "L731"}, {"caller_nid": "impl_pager_allocate_page", "callee": "map_err", "source_file": "src/storage/engine/pager/impl.rs", "source_location": "L733"}, {"caller_nid": "impl_pager_allocate_page", "callee": "InvalidDatabase", "source_file": "src/storage/engine/pager/impl.rs", "source_location": "L735"}, {"caller_nid": "impl_pager_allocate_page", "callee": "to_string", "source_file": "src/storage/engine/pager/impl.rs", "source_location": "L735"}, {"caller_nid": "impl_pager_allocate_page", "callee": "map_err", "source_file": "src/storage/engine/pager/impl.rs", "source_location": "L741"}, {"caller_nid": "impl_pager_allocate_page", "callee": "load_from_trunk", "source_file": "src/storage/engine/pager/impl.rs", "source_location": "L741"}, {"caller_nid": "impl_pager_allocate_page", "callee": "InvalidDatabase", "source_file": "src/storage/engine/pager/impl.rs", "source_location": "L743"}, {"caller_nid": "impl_pager_allocate_page", "callee": "ok_or_else", "source_file": "src/storage/engine/pager/impl.rs", "source_location": "L744"}, {"caller_nid": "impl_pager_allocate_page", "callee": "allocate", "source_file": "src/storage/engine/pager/impl.rs", "source_location": "L744"}, {"caller_nid": "impl_pager_allocate_page", "callee": "InvalidDatabase", "source_file": "src/storage/engine/pager/impl.rs", "source_location": "L745"}, {"caller_nid": "impl_pager_allocate_page", "callee": "to_string", "source_file": "src/storage/engine/pager/impl.rs", "source_location": "L745"}, {"caller_nid": "impl_pager_allocate_page", "callee": "trunk_head", "source_file": "src/storage/engine/pager/impl.rs", "source_location": "L749"}, {"caller_nid": "impl_pager_allocate_page", "callee": "new", "source_file": "src/storage/engine/pager/impl.rs", "source_location": "L763"}, {"caller_nid": "impl_pager_allocate_page", "callee": "insert", "source_file": "src/storage/engine/pager/impl.rs", "source_location": "L766"}, {"caller_nid": "impl_pager_allocate_page", "callee": "clone", "source_file": "src/storage/engine/pager/impl.rs", "source_location": "L766"}, {"caller_nid": "impl_pager_allocate_page", "callee": "mark_dirty", "source_file": "src/storage/engine/pager/impl.rs", "source_location": "L767"}, {"caller_nid": "impl_pager_allocate_page", "callee": "Ok", "source_file": "src/storage/engine/pager/impl.rs", "source_location": "L769"}, {"caller_nid": "impl_pager_free_page", "callee": "Err", "source_file": "src/storage/engine/pager/impl.rs", "source_location": "L775"}, {"caller_nid": "impl_pager_free_page", "callee": "remove", "source_file": "src/storage/engine/pager/impl.rs", "source_location": "L779"}, {"caller_nid": "impl_pager_free_page", "callee": "free", "source_file": "src/storage/engine/pager/impl.rs", "source_location": "L783"}, {"caller_nid": "impl_pager_free_page", "callee": "Ok", "source_file": "src/storage/engine/pager/impl.rs", "source_location": "L787"}, {"caller_nid": "impl_pager_header", "callee": "Ok", "source_file": "src/storage/engine/pager/impl.rs", "source_location": "L792"}, {"caller_nid": "impl_pager_header", "callee": "clone", "source_file": "src/storage/engine/pager/impl.rs", "source_location": "L792"}, {"caller_nid": "impl_pager_physical_header", "callee": "Ok", "source_file": "src/storage/engine/pager/impl.rs", "source_location": "L796"}, {"caller_nid": "impl_pager_update_physical_header", "callee": "Err", "source_file": "src/storage/engine/pager/impl.rs", "source_location": "L801"}, {"caller_nid": "impl_pager_update_physical_header", "callee": "Ok", "source_file": "src/storage/engine/pager/impl.rs", "source_location": "L807"}, {"caller_nid": "impl_pager_page_count", "callee": "Ok", "source_file": "src/storage/engine/pager/impl.rs", "source_location": "L812"}, {"caller_nid": "impl_pager_set_wal_writer", "callee": "unwrap_or_else", "source_file": "src/storage/engine/pager/impl.rs", "source_location": "L827"}, {"caller_nid": "impl_pager_set_wal_writer", "callee": "write", "source_file": "src/storage/engine/pager/impl.rs", "source_location": "L827"}, {"caller_nid": "impl_pager_set_wal_writer", "callee": "into_inner", "source_file": "src/storage/engine/pager/impl.rs", "source_location": "L827"}, {"caller_nid": "impl_pager_set_wal_writer", "callee": "Some", "source_file": "src/storage/engine/pager/impl.rs", "source_location": "L828"}, {"caller_nid": "impl_pager_clear_wal_writer", "callee": "unwrap_or_else", "source_file": "src/storage/engine/pager/impl.rs", "source_location": "L833"}, {"caller_nid": "impl_pager_clear_wal_writer", "callee": "write", "source_file": "src/storage/engine/pager/impl.rs", "source_location": "L833"}, {"caller_nid": "impl_pager_clear_wal_writer", "callee": "into_inner", "source_file": "src/storage/engine/pager/impl.rs", "source_location": "L833"}, {"caller_nid": "impl_pager_has_wal_writer", "callee": "unwrap_or", "source_file": "src/storage/engine/pager/impl.rs", "source_location": "L839"}, {"caller_nid": "impl_pager_has_wal_writer", "callee": "map", "source_file": "src/storage/engine/pager/impl.rs", "source_location": "L839"}, {"caller_nid": "impl_pager_has_wal_writer", "callee": "read", "source_file": "src/storage/engine/pager/impl.rs", "source_location": "L839"}, {"caller_nid": "impl_pager_has_wal_writer", "callee": "is_some", "source_file": "src/storage/engine/pager/impl.rs", "source_location": "L839"}, {"caller_nid": "impl_pager_flush", "callee": "Ok", "source_file": "src/storage/engine/pager/impl.rs", "source_location": "L845"}, {"caller_nid": "impl_pager_flush", "callee": "is_dirty", "source_file": "src/storage/engine/pager/impl.rs", "source_location": "L851"}, {"caller_nid": "impl_pager_flush", "callee": "flush_to_trunks", "source_file": "src/storage/engine/pager/impl.rs", "source_location": "L853"}, {"caller_nid": "impl_pager_flush", "callee": "trunk_head", "source_file": "src/storage/engine/pager/impl.rs", "source_location": "L858"}, {"caller_nid": "impl_pager_flush", "callee": "mark_clean", "source_file": "src/storage/engine/pager/impl.rs", "source_location": "L860"}, {"caller_nid": "impl_pager_flush", "callee": "new", "source_file": "src/storage/engine/pager/impl.rs", "source_location": "L863"}, {"caller_nid": "impl_pager_flush", "callee": "page_id", "source_file": "src/storage/engine/pager/impl.rs", "source_location": "L868"}, {"caller_nid": "impl_pager_flush", "callee": "insert", "source_file": "src/storage/engine/pager/impl.rs", "source_location": "L869"}, {"caller_nid": "impl_pager_flush", "callee": "mark_dirty", "source_file": "src/storage/engine/pager/impl.rs", "source_location": "L870"}, {"caller_nid": "impl_pager_flush", "callee": "flush_dirty", "source_file": "src/storage/engine/pager/impl.rs", "source_location": "L874"}, {"caller_nid": "impl_pager_flush", "callee": "is_empty", "source_file": "src/storage/engine/pager/impl.rs", "source_location": "L875"}, {"caller_nid": "impl_pager_flush", "callee": "unwrap_or", "source_file": "src/storage/engine/pager/impl.rs", "source_location": "L880"}, {"caller_nid": "impl_pager_flush", "callee": "max", "source_file": "src/storage/engine/pager/impl.rs", "source_location": "L880"}, {"caller_nid": "impl_pager_flush", "callee": "filter_map", "source_file": "src/storage/engine/pager/impl.rs", "source_location": "L880"}, {"caller_nid": "impl_pager_flush", "callee": "iter", "source_file": "src/storage/engine/pager/impl.rs", "source_location": "L880"}, {"caller_nid": "impl_pager_flush", "callee": "map", "source_file": "src/storage/engine/pager/impl.rs", "source_location": "L882"}, {"caller_nid": "impl_pager_flush", "callee": "ok", "source_file": "src/storage/engine/pager/impl.rs", "source_location": "L882"}, {"caller_nid": "impl_pager_flush", "callee": "read", "source_file": "src/storage/engine/pager/impl.rs", "source_location": "L886"}, {"caller_nid": "impl_pager_flush", "callee": "as_ref", "source_file": "src/storage/engine/pager/impl.rs", "source_location": "L887"}, {"caller_nid": "impl_pager_flush", "callee": "clone", "source_file": "src/storage/engine/pager/impl.rs", "source_location": "L888"}, {"caller_nid": "impl_pager_flush", "callee": "drop", "source_file": "src/storage/engine/pager/impl.rs", "source_location": "L892"}, {"caller_nid": "impl_pager_flush", "callee": "unwrap_or_else", "source_file": "src/storage/engine/pager/impl.rs", "source_location": "L893"}, {"caller_nid": "impl_pager_flush", "callee": "lock", "source_file": "src/storage/engine/pager/impl.rs", "source_location": "L893"}, {"caller_nid": "impl_pager_flush", "callee": "into_inner", "source_file": "src/storage/engine/pager/impl.rs", "source_location": "L893"}, {"caller_nid": "impl_pager_flush", "callee": "map_err", "source_file": "src/storage/engine/pager/impl.rs", "source_location": "L894"}, {"caller_nid": "impl_pager_flush", "callee": "flush_until", "source_file": "src/storage/engine/pager/impl.rs", "source_location": "L894"}, {"caller_nid": "impl_pager_flush", "callee": "Ok", "source_file": "src/storage/engine/pager/impl.rs", "source_location": "L906"}, {"caller_nid": "impl_pager_sync", "callee": "sync_all", "source_file": "src/storage/engine/pager/impl.rs", "source_location": "L914"}, {"caller_nid": "impl_pager_sync", "callee": "Ok", "source_file": "src/storage/engine/pager/impl.rs", "source_location": "L916"}, {"caller_nid": "impl_pager_cache_stats", "callee": "stats", "source_file": "src/storage/engine/pager/impl.rs", "source_location": "L921"}, {"caller_nid": "impl_pager_file_size", "callee": "Ok", "source_file": "src/storage/engine/pager/impl.rs", "source_location": "L937"}, {"caller_nid": "impl_pager_file_size", "callee": "len", "source_file": "src/storage/engine/pager/impl.rs", "source_location": "L937"}, {"caller_nid": "impl_pager_file_size", "callee": "metadata", "source_file": "src/storage/engine/pager/impl.rs", "source_location": "L937"}, {"caller_nid": "impl_pager_prefetch_hint", "callee": "prefetch_page", "source_file": "src/storage/engine/pager/impl.rs", "source_location": "L949"}, {"caller_nid": "impl_pager_shadow_path", "callee": "into_os_string", "source_file": "src/storage/engine/pager/impl.rs", "source_location": "L961"}, {"caller_nid": "impl_pager_shadow_path", "callee": "to_path_buf", "source_file": "src/storage/engine/pager/impl.rs", "source_location": "L961"}, {"caller_nid": "impl_pager_shadow_path", "callee": "push", "source_file": "src/storage/engine/pager/impl.rs", "source_location": "L962"}, {"caller_nid": "impl_pager_shadow_path", "callee": "from", "source_file": "src/storage/engine/pager/impl.rs", "source_location": "L963"}, {"caller_nid": "impl_pager_meta_shadow_path", "callee": "into_os_string", "source_file": "src/storage/engine/pager/impl.rs", "source_location": "L968"}, {"caller_nid": "impl_pager_meta_shadow_path", "callee": "to_path_buf", "source_file": "src/storage/engine/pager/impl.rs", "source_location": "L968"}, {"caller_nid": "impl_pager_meta_shadow_path", "callee": "push", "source_file": "src/storage/engine/pager/impl.rs", "source_location": "L969"}, {"caller_nid": "impl_pager_meta_shadow_path", "callee": "from", "source_file": "src/storage/engine/pager/impl.rs", "source_location": "L970"}, {"caller_nid": "impl_pager_dwb_path", "callee": "into_os_string", "source_file": "src/storage/engine/pager/impl.rs", "source_location": "L975"}, {"caller_nid": "impl_pager_dwb_path", "callee": "to_path_buf", "source_file": "src/storage/engine/pager/impl.rs", "source_location": "L975"}, {"caller_nid": "impl_pager_dwb_path", "callee": "push", "source_file": "src/storage/engine/pager/impl.rs", "source_location": "L976"}, {"caller_nid": "impl_pager_dwb_path", "callee": "from", "source_file": "src/storage/engine/pager/impl.rs", "source_location": "L977"}, {"caller_nid": "impl_pager_open_dwb_file", "callee": "Ok", "source_file": "src/storage/engine/pager/impl.rs", "source_location": "L985"}, {"caller_nid": "impl_pager_open_dwb_file", "callee": "truncate", "source_file": "src/storage/engine/pager/impl.rs", "source_location": "L985"}, {"caller_nid": "impl_pager_open_dwb_file", "callee": "create", "source_file": "src/storage/engine/pager/impl.rs", "source_location": "L985"}, {"caller_nid": "impl_pager_open_dwb_file", "callee": "write", "source_file": "src/storage/engine/pager/impl.rs", "source_location": "L985"}, {"caller_nid": "impl_pager_open_dwb_file", "callee": "read", "source_file": "src/storage/engine/pager/impl.rs", "source_location": "L985"}, {"caller_nid": "impl_pager_open_dwb_file", "callee": "new", "source_file": "src/storage/engine/pager/impl.rs", "source_location": "L985"}, {"caller_nid": "impl_pager_clear_dwb_file", "callee": "set_len", "source_file": "src/storage/engine/pager/impl.rs", "source_location": "L995"}, {"caller_nid": "impl_pager_clear_dwb_file", "callee": "seek", "source_file": "src/storage/engine/pager/impl.rs", "source_location": "L996"}, {"caller_nid": "impl_pager_clear_dwb_file", "callee": "Start", "source_file": "src/storage/engine/pager/impl.rs", "source_location": "L996"}, {"caller_nid": "impl_pager_clear_dwb_file", "callee": "sync_all", "source_file": "src/storage/engine/pager/impl.rs", "source_location": "L997"}, {"caller_nid": "impl_pager_clear_dwb_file", "callee": "Ok", "source_file": "src/storage/engine/pager/impl.rs", "source_location": "L998"}, {"caller_nid": "impl_pager_write_header_shadow", "callee": "Ok", "source_file": "src/storage/engine/pager/impl.rs", "source_location": "L1004"}, {"caller_nid": "impl_pager_write_header_shadow", "callee": "create", "source_file": "src/storage/engine/pager/impl.rs", "source_location": "L1007"}, {"caller_nid": "impl_pager_write_header_shadow", "callee": "write_all", "source_file": "src/storage/engine/pager/impl.rs", "source_location": "L1008"}, {"caller_nid": "impl_pager_write_header_shadow", "callee": "as_bytes", "source_file": "src/storage/engine/pager/impl.rs", "source_location": "L1008"}, {"caller_nid": "impl_pager_write_header_shadow", "callee": "sync_all", "source_file": "src/storage/engine/pager/impl.rs", "source_location": "L1009"}, {"caller_nid": "impl_pager_write_header_shadow", "callee": "Ok", "source_file": "src/storage/engine/pager/impl.rs", "source_location": "L1010"}, {"caller_nid": "impl_pager_recover_header_from_shadow", "callee": "exists", "source_file": "src/storage/engine/pager/impl.rs", "source_location": "L1016"}, {"caller_nid": "impl_pager_recover_header_from_shadow", "callee": "Err", "source_file": "src/storage/engine/pager/impl.rs", "source_location": "L1017"}, {"caller_nid": "impl_pager_recover_header_from_shadow", "callee": "InvalidDatabase", "source_file": "src/storage/engine/pager/impl.rs", "source_location": "L1017"}, {"caller_nid": "impl_pager_recover_header_from_shadow", "callee": "into", "source_file": "src/storage/engine/pager/impl.rs", "source_location": "L1018"}, {"caller_nid": "impl_pager_recover_header_from_shadow", "callee": "read_exact", "source_file": "src/storage/engine/pager/impl.rs", "source_location": "L1023"}, {"caller_nid": "impl_pager_recover_header_from_shadow", "callee": "from_bytes", "source_file": "src/storage/engine/pager/impl.rs", "source_location": "L1024"}, {"caller_nid": "impl_pager_recover_header_from_shadow", "callee": "as_bytes", "source_file": "src/storage/engine/pager/impl.rs", "source_location": "L1027"}, {"caller_nid": "impl_pager_recover_header_from_shadow", "callee": "Err", "source_file": "src/storage/engine/pager/impl.rs", "source_location": "L1029"}, {"caller_nid": "impl_pager_recover_header_from_shadow", "callee": "InvalidDatabase", "source_file": "src/storage/engine/pager/impl.rs", "source_location": "L1029"}, {"caller_nid": "impl_pager_recover_header_from_shadow", "callee": "into", "source_file": "src/storage/engine/pager/impl.rs", "source_location": "L1030"}, {"caller_nid": "impl_pager_recover_header_from_shadow", "callee": "sync_all", "source_file": "src/storage/engine/pager/impl.rs", "source_location": "L1038"}, {"caller_nid": "impl_pager_recover_header_from_shadow", "callee": "Ok", "source_file": "src/storage/engine/pager/impl.rs", "source_location": "L1041"}, {"caller_nid": "impl_pager_write_meta_shadow", "callee": "Ok", "source_file": "src/storage/engine/pager/impl.rs", "source_location": "L1047"}, {"caller_nid": "impl_pager_write_meta_shadow", "callee": "create", "source_file": "src/storage/engine/pager/impl.rs", "source_location": "L1050"}, {"caller_nid": "impl_pager_write_meta_shadow", "callee": "write_all", "source_file": "src/storage/engine/pager/impl.rs", "source_location": "L1051"}, {"caller_nid": "impl_pager_write_meta_shadow", "callee": "as_bytes", "source_file": "src/storage/engine/pager/impl.rs", "source_location": "L1051"}, {"caller_nid": "impl_pager_write_meta_shadow", "callee": "sync_all", "source_file": "src/storage/engine/pager/impl.rs", "source_location": "L1052"}, {"caller_nid": "impl_pager_write_meta_shadow", "callee": "Ok", "source_file": "src/storage/engine/pager/impl.rs", "source_location": "L1053"}, {"caller_nid": "impl_pager_recover_meta_from_shadow", "callee": "exists", "source_file": "src/storage/engine/pager/impl.rs", "source_location": "L1059"}, {"caller_nid": "impl_pager_recover_meta_from_shadow", "callee": "Err", "source_file": "src/storage/engine/pager/impl.rs", "source_location": "L1060"}, {"caller_nid": "impl_pager_recover_meta_from_shadow", "callee": "InvalidDatabase", "source_file": "src/storage/engine/pager/impl.rs", "source_location": "L1060"}, {"caller_nid": "impl_pager_recover_meta_from_shadow", "callee": "into", "source_file": "src/storage/engine/pager/impl.rs", "source_location": "L1061"}, {"caller_nid": "impl_pager_recover_meta_from_shadow", "callee": "read_exact", "source_file": "src/storage/engine/pager/impl.rs", "source_location": "L1066"}, {"caller_nid": "impl_pager_recover_meta_from_shadow", "callee": "from_bytes", "source_file": "src/storage/engine/pager/impl.rs", "source_location": "L1067"}, {"caller_nid": "impl_pager_recover_meta_from_shadow", "callee": "sync_all", "source_file": "src/storage/engine/pager/impl.rs", "source_location": "L1073"}, {"caller_nid": "impl_pager_recover_meta_from_shadow", "callee": "Ok", "source_file": "src/storage/engine/pager/impl.rs", "source_location": "L1076"}, {"caller_nid": "impl_pager_write_pages_through_dwb", "callee": "map_err", "source_file": "src/storage/engine/pager/impl.rs", "source_location": "L1087"}, {"caller_nid": "impl_pager_write_pages_through_dwb", "callee": "lock", "source_file": "src/storage/engine/pager/impl.rs", "source_location": "L1087"}, {"caller_nid": "impl_pager_write_pages_through_dwb", "callee": "len", "source_file": "src/storage/engine/pager/impl.rs", "source_location": "L1093"}, {"caller_nid": "impl_pager_write_pages_through_dwb", "callee": "with_capacity", "source_file": "src/storage/engine/pager/impl.rs", "source_location": "L1094"}, {"caller_nid": "impl_pager_write_pages_through_dwb", "callee": "extend_from_slice", "source_file": "src/storage/engine/pager/impl.rs", "source_location": "L1097"}, {"caller_nid": "impl_pager_write_pages_through_dwb", "callee": "extend_from_slice", "source_file": "src/storage/engine/pager/impl.rs", "source_location": "L1098"}, {"caller_nid": "impl_pager_write_pages_through_dwb", "callee": "to_le_bytes", "source_file": "src/storage/engine/pager/impl.rs", "source_location": "L1098"}, {"caller_nid": "impl_pager_write_pages_through_dwb", "callee": "len", "source_file": "src/storage/engine/pager/impl.rs", "source_location": "L1098"}, {"caller_nid": "impl_pager_write_pages_through_dwb", "callee": "extend_from_slice", "source_file": "src/storage/engine/pager/impl.rs", "source_location": "L1099"}, {"caller_nid": "impl_pager_write_pages_through_dwb", "callee": "extend_from_slice", "source_file": "src/storage/engine/pager/impl.rs", "source_location": "L1103"}, {"caller_nid": "impl_pager_write_pages_through_dwb", "callee": "to_le_bytes", "source_file": "src/storage/engine/pager/impl.rs", "source_location": "L1103"}, {"caller_nid": "impl_pager_write_pages_through_dwb", "callee": "extend_from_slice", "source_file": "src/storage/engine/pager/impl.rs", "source_location": "L1104"}, {"caller_nid": "impl_pager_write_pages_through_dwb", "callee": "as_bytes", "source_file": "src/storage/engine/pager/impl.rs", "source_location": "L1104"}, {"caller_nid": "impl_pager_write_pages_through_dwb", "callee": "crc32", "source_file": "src/storage/engine/pager/impl.rs", "source_location": "L1108"}, {"caller_nid": "impl_pager_write_pages_through_dwb", "callee": "copy_from_slice", "source_file": "src/storage/engine/pager/impl.rs", "source_location": "L1109"}, {"caller_nid": "impl_pager_write_pages_through_dwb", "callee": "to_le_bytes", "source_file": "src/storage/engine/pager/impl.rs", "source_location": "L1109"}, {"caller_nid": "impl_pager_write_pages_through_dwb", "callee": "seek", "source_file": "src/storage/engine/pager/impl.rs", "source_location": "L1112"}, {"caller_nid": "impl_pager_write_pages_through_dwb", "callee": "Start", "source_file": "src/storage/engine/pager/impl.rs", "source_location": "L1112"}, {"caller_nid": "impl_pager_write_pages_through_dwb", "callee": "write_all", "source_file": "src/storage/engine/pager/impl.rs", "source_location": "L1113"}, {"caller_nid": "impl_pager_write_pages_through_dwb", "callee": "set_len", "source_file": "src/storage/engine/pager/impl.rs", "source_location": "L1114"}, {"caller_nid": "impl_pager_write_pages_through_dwb", "callee": "len", "source_file": "src/storage/engine/pager/impl.rs", "source_location": "L1114"}, {"caller_nid": "impl_pager_write_pages_through_dwb", "callee": "sync_all", "source_file": "src/storage/engine/pager/impl.rs", "source_location": "L1115"}, {"caller_nid": "impl_pager_write_pages_through_dwb", "callee": "Ok", "source_file": "src/storage/engine/pager/impl.rs", "source_location": "L1125"}, {"caller_nid": "impl_pager_write_pages_through_dwb", "callee": "Ok", "source_file": "src/storage/engine/pager/impl.rs", "source_location": "L1131"}, {"caller_nid": "impl_pager_recover_from_dwb", "callee": "exists", "source_file": "src/storage/engine/pager/impl.rs", "source_location": "L1141"}, {"caller_nid": "impl_pager_recover_from_dwb", "callee": "Ok", "source_file": "src/storage/engine/pager/impl.rs", "source_location": "L1142"}, {"caller_nid": "impl_pager_recover_from_dwb", "callee": "map_err", "source_file": "src/storage/engine/pager/impl.rs", "source_location": "L1146"}, {"caller_nid": "impl_pager_recover_from_dwb", "callee": "lock", "source_file": "src/storage/engine/pager/impl.rs", "source_location": "L1146"}, {"caller_nid": "impl_pager_recover_from_dwb", "callee": "write", "source_file": "src/storage/engine/pager/impl.rs", "source_location": "L1150"}, {"caller_nid": "impl_pager_recover_from_dwb", "callee": "read", "source_file": "src/storage/engine/pager/impl.rs", "source_location": "L1150"}, {"caller_nid": "impl_pager_recover_from_dwb", "callee": "new", "source_file": "src/storage/engine/pager/impl.rs", "source_location": "L1150"}, {"caller_nid": "impl_pager_recover_from_dwb_file", "callee": "seek", "source_file": "src/storage/engine/pager/impl.rs", "source_location": "L1155"}, {"caller_nid": "impl_pager_recover_from_dwb_file", "callee": "Start", "source_file": "src/storage/engine/pager/impl.rs", "source_location": "L1155"}, {"caller_nid": "impl_pager_recover_from_dwb_file", "callee": "len", "source_file": "src/storage/engine/pager/impl.rs", "source_location": "L1156"}, {"caller_nid": "impl_pager_recover_from_dwb_file", "callee": "metadata", "source_file": "src/storage/engine/pager/impl.rs", "source_location": "L1156"}, {"caller_nid": "impl_pager_recover_from_dwb_file", "callee": "read_exact", "source_file": "src/storage/engine/pager/impl.rs", "source_location": "L1163"}, {"caller_nid": "impl_pager_recover_from_dwb_file", "callee": "from_le_bytes", "source_file": "src/storage/engine/pager/impl.rs", "source_location": "L1171"}, {"caller_nid": "impl_pager_recover_from_dwb_file", "callee": "from_le_bytes", "source_file": "src/storage/engine/pager/impl.rs", "source_location": "L1172"}, {"caller_nid": "impl_pager_recover_from_dwb_file", "callee": "len", "source_file": "src/storage/engine/pager/impl.rs", "source_location": "L1178"}, {"caller_nid": "impl_pager_recover_from_dwb_file", "callee": "crc32", "source_file": "src/storage/engine/pager/impl.rs", "source_location": "L1184"}, {"caller_nid": "impl_pager_recover_from_dwb_file", "callee": "from_le_bytes", "source_file": "src/storage/engine/pager/impl.rs", "source_location": "L1193"}, {"caller_nid": "impl_pager_recover_from_dwb_file", "callee": "copy_from_slice", "source_file": "src/storage/engine/pager/impl.rs", "source_location": "L1202"}, {"caller_nid": "impl_pager_recover_from_dwb_file", "callee": "from_bytes", "source_file": "src/storage/engine/pager/impl.rs", "source_location": "L1205"}, {"caller_nid": "impl_pager_recover_from_dwb_file", "callee": "sync_all", "source_file": "src/storage/engine/pager/impl.rs", "source_location": "L1212"}, {"caller_nid": "impl_pager_write_header_and_sync", "callee": "sync_all", "source_file": "src/storage/engine/pager/impl.rs", "source_location": "L1222"}, {"caller_nid": "impl_pager_write_header_and_sync", "callee": "Ok", "source_file": "src/storage/engine/pager/impl.rs", "source_location": "L1223"}, {"caller_nid": "impl_pager_set_checkpoint_in_progress", "callee": "drop", "source_file": "src/storage/engine/pager/impl.rs", "source_location": "L1236"}, {"caller_nid": "impl_pager_complete_checkpoint", "callee": "drop", "source_file": "src/storage/engine/pager/impl.rs", "source_location": "L1247"}]}